pypicontents/__init__.py
pypicontents/cli.py
pypicontents/wrapper.py
pypicontents/api/__init__.py
pypicontents/api/errors.py
pypicontents/api/merge.py
pypicontents/api/pypi.py
pypicontents/api/stats.py
pypicontents/api/stdlib.py
pypicontents/core/__init__.py
pypicontents/core/logger.py
pypicontents/core/patches.py
pypicontents/core/utils.py
pypicontents-0.2.0.dist-info/AUTHORS.rst
pypicontents-0.2.0.dist-info/LICENSE
pypicontents-0.2.0.dist-info/METADATA
pypicontents-0.2.0.dist-info/WHEEL
pypicontents-0.2.0.dist-info/entry_points.txt
pypicontents-0.2.0.dist-info/top_level.txt
pypicontents-0.2.0.dist-info/RECORD
