Metadata-Version: 2.1
Name: pypicontents
Version: 0.2.0
Summary: PyPIContents is an application that generates a Module Index from the Python Package Index (PyPI) and also from various versions of the Python Standard Library.
Home-page: https://github.com/LuisAlejandro/pypicontents
Author: Luis Alejandro Martínez Faneyth
Author-email: luis@collagelabs.org
License: GNU GENERAL PUBLIC LICENSE
Keywords: PyPI,module,index
Platform: posix
Platform: linux
Classifier: Development Status :: 5 - Production/Stable
Classifier: Intended Audience :: Developers
Classifier: License :: OSI Approved :: GNU General Public License v3 (GPLv3)
Classifier: Natural Language :: English
Classifier: Programming Language :: Python :: 3
Classifier: Programming Language :: Python :: 3.8
Classifier: Programming Language :: Python :: 3.9
Classifier: Programming Language :: Python :: 3.10
Classifier: Programming Language :: Python :: 3.11
License-File: LICENSE
License-File: AUTHORS.rst
Requires-Dist: setuptools (==62.1.0)
